BabyStep/__init__.py
BabyStep/ef.py
BabyStep-0.0.3.dist-info/LICENSE
BabyStep-0.0.3.dist-info/METADATA
BabyStep-0.0.3.dist-info/WHEEL
BabyStep-0.0.3.dist-info/top_level.txt
BabyStep-0.0.3.dist-info/RECORD
